watermelon/__init__.py
Watermelon-0.0.1.dist-info/LICENSE.txt
Watermelon-0.0.1.dist-info/METADATA
Watermelon-0.0.1.dist-info/WHEEL
Watermelon-0.0.1.dist-info/top_level.txt
Watermelon-0.0.1.dist-info/RECORD
